QMarkdownView/__init__.py
QMarkdownView/resources.py
QMarkdownView-0.2.dist-info/LICENSE
QMarkdownView-0.2.dist-info/METADATA
QMarkdownView-0.2.dist-info/WHEEL
QMarkdownView-0.2.dist-info/top_level.txt
QMarkdownView-0.2.dist-info/RECORD
