Metadata-Version: 2.1
Name: QMarkdownView
Version: 0.2
Summary: a package based on PySide6 designed to help you preview Markdown documents.
Home-page: https://github.com/hellojudger/QMarkdownView/
Author: xiezheyuan
Author-email: xiezheyuan09@163.com
Classifier: Programming Language :: Python :: 3
Classifier: License :: OSI Approved :: MIT License
Classifier: Operating System :: OS Independent
Classifier: Environment :: X11 Applications :: Qt
Classifier: Topic :: Text Processing :: Markup :: Markdown
License-File: LICENSE
Requires-Dist: PySide6
Requires-Dist: markdown
